mvg_monitor/__init__.py
mvg_monitor/interface.py
mvg_monitor/monitor.py
mvg_cli_departures-0.3.dist-info/LICENSE
mvg_cli_departures-0.3.dist-info/METADATA
mvg_cli_departures-0.3.dist-info/WHEEL
mvg_cli_departures-0.3.dist-info/entry_points.txt
mvg_cli_departures-0.3.dist-info/top_level.txt
mvg_cli_departures-0.3.dist-info/RECORD
