Metadata-Version: 2.1
Name: mvg-cli-departures
Version: 0.3
Summary: Command line departure monitor for the MVG - munich's public transport
Home-page: https://gitlab.com/maternusherold/mvg-command-line-departure-monitor
Author: Turnman H
Author-email: turnmanh@gmail.com
License: MIT
Platform: UNKNOWN
Requires-Dist: mvg-api
